plover_vi/__init__.py
plover_vi/analysis.py
plover_vi/bigram_filter.py
plover_vi/bigram_frequency.py
plover_vi/config.py
plover_vi/construct_2_syllable_brief_system.py
plover_vi/decompose.py
plover_vi/dictionary.py
plover_vi/generate_brief.py
plover_vi/initialize_independent_script.py
plover_vi/library.py
plover_vi/stroke.py
plover_vi-0.2.2.dist-info/LICENSE
plover_vi-0.2.2.dist-info/METADATA
plover_vi-0.2.2.dist-info/WHEEL
plover_vi-0.2.2.dist-info/top_level.txt
plover_vi-0.2.2.dist-info/zip-safe
plover_vi-0.2.2.dist-info/RECORD
