Metadata-Version: 2.1
Name: plover-vi
Version: 0.2.2
Summary: Vietnamese system for Plover
Home-page: UNKNOWN
Author: user202729
License: GNU General Public License v3 or later (GPLv3+)
Keywords: plover plover_plugin
Platform: UNKNOWN
Classifier: Environment :: Plugins
Classifier: Intended Audience :: End Users/Desktop
Classifier: Operating System :: OS Independent
Classifier: Programming Language :: Python :: 3
Requires-Dist: plover (>=4.0.0.dev8)
Requires-Dist: plover-python-dictionary (>=1.0.0)
Requires-Dist: plover-stroke (>=0.4.0)
